{
  "@type": "type.googleapis.com/google.cloud.speech.v1.LongRunningRecognizeResponse",
  "results": [
    {
      "alternatives": [
        {
          "confidence": 0.74193823,
          "transcript": "bu \u00e7al\u0131\u015fmaya kat\u0131lanlar\u0131n kabul etti\u011fin i\u00e7in te\u015fekk\u00fcr ederiz",
          "words": [
            {
              "endTime": "1.700s",
              "startTime": "1.300s",
              "word": "bu"
            },
            {
              "endTime": "4.600s",
              "startTime": "1.700s",
              "word": "\u00e7al\u0131\u015fmaya"
            },
            {
              "endTime": "5.200s",
              "startTime": "4.600s",
              "word": "kat\u0131lanlar\u0131n"
            },
            {
              "endTime": "5.700s",
              "startTime": "5.200s",
              "word": "kabul"
            },
            {
              "endTime": "6.200s",
              "startTime": "5.700s",
              "word": "etti\u011fin"
            },
            {
              "endTime": "6.500s",
              "startTime": "6.200s",
              "word": "i\u00e7in"
            },
            {
              "endTime": "7s",
              "startTime": "6.500s",
              "word": "te\u015fekk\u00fcr"
            },
            {
              "endTime": "7.300s",
              "startTime": "7s",
              "word": "ederiz"
            }
          ]
        }
      ]
    },
    {
      "alternatives": [
        {
          "confidence": 0.84985805,
          "transcript": " l\u00fctfen her sayfa size verecek di\u011ferleri tan\u0131d\u0131ktan sonra Bo\u015fluk tu\u015funa bas\u0131n buraya neden geldiniz anlat\u0131r m\u0131s\u0131n\u0131z Neden geldi",
          "words": [
            {
              "endTime": "10.200s",
              "startTime": "9.500s",
              "word": "l\u00fctfen"
            },
            {
              "endTime": "10.400s",
              "startTime": "10.200s",
              "word": "her"
            },
            {
              "endTime": "10.700s",
              "startTime": "10.400s",
              "word": "sayfa"
            },
            {
              "endTime": "11.100s",
              "startTime": "10.700s",
              "word": "size"
            },
            {
              "endTime": "11.800s",
              "startTime": "11.100s",
              "word": "verecek"
            },
            {
              "endTime": "12.500s",
              "startTime": "11.800s",
              "word": "di\u011ferleri"
            },
            {
              "endTime": "13.700s",
              "startTime": "12.500s",
              "word": "tan\u0131d\u0131ktan"
            },
            {
              "endTime": "13.900s",
              "startTime": "13.700s",
              "word": "sonra"
            },
            {
              "endTime": "14.800s",
              "startTime": "13.900s",
              "word": "Bo\u015fluk"
            },
            {
              "endTime": "15.300s",
              "startTime": "14.800s",
              "word": "tu\u015funa"
            },
            {
              "endTime": "15.900s",
              "startTime": "15.300s",
              "word": "bas\u0131n"
            },
            {
              "endTime": "18.400s",
              "startTime": "15.900s",
              "word": "buraya"
            },
            {
              "endTime": "18.800s",
              "startTime": "18.400s",
              "word": "neden"
            },
            {
              "endTime": "19.300s",
              "startTime": "18.800s",
              "word": "geldiniz"
            },
            {
              "endTime": "20s",
              "startTime": "19.300s",
              "word": "anlat\u0131r"
            },
            {
              "endTime": "20.400s",
              "startTime": "20s",
              "word": "m\u0131s\u0131n\u0131z"
            },
            {
              "endTime": "21s",
              "startTime": "20.400s",
              "word": "Neden"
            },
            {
              "endTime": "21.500s",
              "startTime": "21s",
              "word": "geldi"
            }
          ]
        }
      ]
    },
    {
      "alternatives": [
        {
          "confidence": 0.84392804,
          "transcript": " gelecek olan sayfa 2 sayfadaki resmi anlat\u0131r m\u0131s\u0131n\u0131z size size neler d\u00fc\u015f\u00fcnd\u00fcr\u00fcyor beni sinir amca odalara kendimi g\u00fczelli\u011fine tutmu\u015f Durmu\u015f Bilmiyorum art\u0131k ne yap\u0131yor k\u00f6t\u00fc Bir hat\u0131rlat\u0131r m\u0131s\u0131n",
          "words": [
            {
              "endTime": "29s",
              "startTime": "26.700s",
              "word": "gelecek"
            },
            {
              "endTime": "29.500s",
              "startTime": "29s",
              "word": "olan"
            },
            {
              "endTime": "29.900s",
              "startTime": "29.500s",
              "word": "sayfa"
            },
            {
              "endTime": "30.200s",
              "startTime": "29.900s",
              "word": "2"
            },
            {
              "endTime": "30.900s",
              "startTime": "30.200s",
              "word": "sayfadaki"
            },
            {
              "endTime": "31.700s",
              "startTime": "30.900s",
              "word": "resmi"
            },
            {
              "endTime": "32.200s",
              "startTime": "31.700s",
              "word": "anlat\u0131r"
            },
            {
              "endTime": "32.700s",
              "startTime": "32.200s",
              "word": "m\u0131s\u0131n\u0131z"
            },
            {
              "endTime": "33.600s",
              "startTime": "32.700s",
              "word": "size"
            },
            {
              "endTime": "34s",
              "startTime": "33.600s",
              "word": "size"
            },
            {
              "endTime": "34.400s",
              "startTime": "34s",
              "word": "neler"
            },
            {
              "endTime": "35.400s",
              "startTime": "34.400s",
              "word": "d\u00fc\u015f\u00fcnd\u00fcr\u00fcyor"
            },
            {
              "endTime": "35.800s",
              "startTime": "35.400s",
              "word": "beni"
            },
            {
              "endTime": "36.300s",
              "startTime": "35.800s",
              "word": "sinir"
            },
            {
              "endTime": "39.100s",
              "startTime": "36.300s",
              "word": "amca"
            },
            {
              "endTime": "39.700s",
              "startTime": "39.100s",
              "word": "odalara"
            },
            {
              "endTime": "40.100s",
              "startTime": "39.700s",
              "word": "kendimi"
            },
            {
              "endTime": "40.900s",
              "startTime": "40.100s",
              "word": "g\u00fczelli\u011fine"
            },
            {
              "endTime": "41.300s",
              "startTime": "40.900s",
              "word": "tutmu\u015f"
            },
            {
              "endTime": "42.200s",
              "startTime": "41.300s",
              "word": "Durmu\u015f"
            },
            {
              "endTime": "43s",
              "startTime": "42.200s",
              "word": "Bilmiyorum"
            },
            {
              "endTime": "43.200s",
              "startTime": "43s",
              "word": "art\u0131k"
            },
            {
              "endTime": "43.300s",
              "startTime": "43.200s",
              "word": "ne"
            },
            {
              "endTime": "43.700s",
              "startTime": "43.300s",
              "word": "yap\u0131yor"
            },
            {
              "endTime": "46.100s",
              "startTime": "43.700s",
              "word": "k\u00f6t\u00fc"
            },
            {
              "endTime": "46.300s",
              "startTime": "46.100s",
              "word": "Bir"
            },
            {
              "endTime": "47.200s",
              "startTime": "46.300s",
              "word": "hat\u0131rlat\u0131r"
            },
            {
              "endTime": "47.600s",
              "startTime": "47.200s",
              "word": "m\u0131s\u0131n"
            }
          ]
        }
      ]
    },
    {
      "alternatives": [
        {
          "confidence": 0.898716,
          "transcript": " 1'den 30'a kadar sayar m\u0131s\u0131n\u0131z 12345678 10 11 12 13 14 16 17 30 1 2 3 4 5 6 7 8 9 10 11 12 13 14 15 16 17 18 66 gelecek olan sayfadaki y\u00f6resinin anlat\u0131r m\u0131s\u0131n\u0131z siz de size neler d\u00fc\u015f\u00fcnd\u00fc\u011f\u00fcn\u00fcz\u00fc ne hissettirir",
          "words": [
            {
              "endTime": "52.300s",
              "startTime": "48.700s",
              "word": "1'den"
            },
            {
              "endTime": "52.800s",
              "startTime": "52.300s",
              "word": "30'a"
            },
            {
              "endTime": "53s",
              "startTime": "52.800s",
              "word": "kadar"
            },
            {
              "endTime": "53.400s",
              "startTime": "53s",
              "word": "sayar"
            },
            {
              "endTime": "53.700s",
              "startTime": "53.400s",
              "word": "m\u0131s\u0131n\u0131z"
            },
            {
              "endTime": "55.100s",
              "startTime": "53.700s",
              "word": "12345678"
            },
            {
              "endTime": "55.400s",
              "startTime": "55.100s",
              "word": "10"
            },
            {
              "endTime": "55.600s",
              "startTime": "55.400s",
              "word": "11"
            },
            {
              "endTime": "55.700s",
              "startTime": "55.600s",
              "word": "12"
            },
            {
              "endTime": "55.900s",
              "startTime": "55.700s",
              "word": "13"
            },
            {
              "endTime": "56s",
              "startTime": "55.900s",
              "word": "14"
            },
            {
              "endTime": "56.700s",
              "startTime": "56s",
              "word": "16"
            },
            {
              "endTime": "57s",
              "startTime": "56.700s",
              "word": "17"
            },
            {
              "endTime": "61.500s",
              "startTime": "57s",
              "word": "30"
            },
            {
              "endTime": "64s",
              "startTime": "61.500s",
              "word": "1"
            },
            {
              "endTime": "64.200s",
              "startTime": "64s",
              "word": "2"
            },
            {
              "endTime": "64.400s",
              "startTime": "64.200s",
              "word": "3"
            },
            {
              "endTime": "64.500s",
              "startTime": "64.400s",
              "word": "4"
            },
            {
              "endTime": "64.800s",
              "startTime": "64.500s",
              "word": "5"
            },
            {
              "endTime": "64.900s",
              "startTime": "64.800s",
              "word": "6"
            },
            {
              "endTime": "65.300s",
              "startTime": "64.900s",
              "word": "7"
            },
            {
              "endTime": "65.500s",
              "startTime": "65.300s",
              "word": "8"
            },
            {
              "endTime": "65.700s",
              "startTime": "65.500s",
              "word": "9"
            },
            {
              "endTime": "66s",
              "startTime": "65.700s",
              "word": "10"
            },
            {
              "endTime": "66.100s",
              "startTime": "66s",
              "word": "11"
            },
            {
              "endTime": "66.400s",
              "startTime": "66.100s",
              "word": "12"
            },
            {
              "endTime": "66.900s",
              "startTime": "66.400s",
              "word": "13"
            },
            {
              "endTime": "67.100s",
              "startTime": "66.900s",
              "word": "14"
            },
            {
              "endTime": "67.500s",
              "startTime": "67.100s",
              "word": "15"
            },
            {
              "endTime": "67.600s",
              "startTime": "67.500s",
              "word": "16"
            },
            {
              "endTime": "68s",
              "startTime": "67.600s",
              "word": "17"
            },
            {
              "endTime": "68.200s",
              "startTime": "68s",
              "word": "18"
            },
            {
              "endTime": "70.700s",
              "startTime": "68.200s",
              "word": "66"
            },
            {
              "endTime": "74.800s",
              "startTime": "70.700s",
              "word": "gelecek"
            },
            {
              "endTime": "75.100s",
              "startTime": "74.800s",
              "word": "olan"
            },
            {
              "endTime": "75.600s",
              "startTime": "75.100s",
              "word": "sayfadaki"
            },
            {
              "endTime": "76.400s",
              "startTime": "75.600s",
              "word": "y\u00f6resinin"
            },
            {
              "endTime": "76.900s",
              "startTime": "76.400s",
              "word": "anlat\u0131r"
            },
            {
              "endTime": "77.300s",
              "startTime": "76.900s",
              "word": "m\u0131s\u0131n\u0131z"
            },
            {
              "endTime": "77.500s",
              "startTime": "77.300s",
              "word": "siz"
            },
            {
              "endTime": "77.900s",
              "startTime": "77.500s",
              "word": "de"
            },
            {
              "endTime": "78.500s",
              "startTime": "77.900s",
              "word": "size"
            },
            {
              "endTime": "78.900s",
              "startTime": "78.500s",
              "word": "neler"
            },
            {
              "endTime": "79.700s",
              "startTime": "78.900s",
              "word": "d\u00fc\u015f\u00fcnd\u00fc\u011f\u00fcn\u00fcz\u00fc"
            },
            {
              "endTime": "80.200s",
              "startTime": "79.700s",
              "word": "ne"
            },
            {
              "endTime": "80.800s",
              "startTime": "80.200s",
              "word": "hissettirir"
            }
          ]
        }
      ]
    },
    {
      "alternatives": [
        {
          "confidence": 0.7696323,
          "transcript": " Burada biri var \u00e7ocuklar var 12345678 8 ayda yani",
          "words": [
            {
              "endTime": "83.400s",
              "startTime": "82.900s",
              "word": "Burada"
            },
            {
              "endTime": "83.700s",
              "startTime": "83.400s",
              "word": "biri"
            },
            {
              "endTime": "84.800s",
              "startTime": "83.700s",
              "word": "var"
            },
            {
              "endTime": "85.400s",
              "startTime": "84.800s",
              "word": "\u00e7ocuklar"
            },
            {
              "endTime": "85.500s",
              "startTime": "85.400s",
              "word": "var"
            },
            {
              "endTime": "90.300s",
              "startTime": "85.500s",
              "word": "12345678"
            },
            {
              "endTime": "91.500s",
              "startTime": "90.300s",
              "word": "8"
            },
            {
              "endTime": "91.800s",
              "startTime": "91.500s",
              "word": "ayda"
            },
            {
              "endTime": "92.300s",
              "startTime": "91.800s",
              "word": "yani"
            }
          ]
        }
      ]
    },
    {
      "alternatives": [
        {
          "confidence": 0.8324349,
          "transcript": " evet \u00f6yle horozlar yan\u0131nda var orada uydurmu\u015flar birlikte hepsi bir haftay\u0131 ma\u00e7lar\u0131na baksana hepsini yatakta olmu\u015f \u00c7ok g\u00fczel ya\u015famas\u0131n\u0131 en g\u00fczel hat\u0131rlat\u0131r misiniz",
          "words": [
            {
              "endTime": "95.100s",
              "startTime": "94.500s",
              "word": "evet"
            },
            {
              "endTime": "95.300s",
              "startTime": "95.100s",
              "word": "\u00f6yle"
            },
            {
              "endTime": "96.200s",
              "startTime": "95.300s",
              "word": "horozlar"
            },
            {
              "endTime": "96.900s",
              "startTime": "96.200s",
              "word": "yan\u0131nda"
            },
            {
              "endTime": "97.100s",
              "startTime": "96.900s",
              "word": "var"
            },
            {
              "endTime": "98.300s",
              "startTime": "97.100s",
              "word": "orada"
            },
            {
              "endTime": "99s",
              "startTime": "98.300s",
              "word": "uydurmu\u015flar"
            },
            {
              "endTime": "99.500s",
              "startTime": "99s",
              "word": "birlikte"
            },
            {
              "endTime": "99.800s",
              "startTime": "99.500s",
              "word": "hepsi"
            },
            {
              "endTime": "100s",
              "startTime": "99.800s",
              "word": "bir"
            },
            {
              "endTime": "100.500s",
              "startTime": "100s",
              "word": "haftay\u0131"
            },
            {
              "endTime": "101.100s",
              "startTime": "100.500s",
              "word": "ma\u00e7lar\u0131na"
            },
            {
              "endTime": "101.400s",
              "startTime": "101.100s",
              "word": "baksana"
            },
            {
              "endTime": "101.900s",
              "startTime": "101.400s",
              "word": "hepsini"
            },
            {
              "endTime": "102.500s",
              "startTime": "101.900s",
              "word": "yatakta"
            },
            {
              "endTime": "102.900s",
              "startTime": "102.500s",
              "word": "olmu\u015f"
            },
            {
              "endTime": "104s",
              "startTime": "102.900s",
              "word": "\u00c7ok"
            },
            {
              "endTime": "104.300s",
              "startTime": "104s",
              "word": "g\u00fczel"
            },
            {
              "endTime": "106.200s",
              "startTime": "104.300s",
              "word": "ya\u015famas\u0131n\u0131"
            },
            {
              "endTime": "107.200s",
              "startTime": "106.200s",
              "word": "en"
            },
            {
              "endTime": "107.600s",
              "startTime": "107.200s",
              "word": "g\u00fczel"
            },
            {
              "endTime": "108.800s",
              "startTime": "107.600s",
              "word": "hat\u0131rlat\u0131r"
            },
            {
              "endTime": "108.900s",
              "startTime": "108.800s",
              "word": "misiniz"
            }
          ]
        }
      ]
    },
    {
      "alternatives": [
        {
          "confidence": 0.4963476,
          "transcript": " Anlad\u0131m biraz anlat\u0131r m\u0131s\u0131n",
          "words": [
            {
              "endTime": "111.600s",
              "startTime": "110.900s",
              "word": "Anlad\u0131m"
            },
            {
              "endTime": "112.800s",
              "startTime": "111.600s",
              "word": "biraz"
            },
            {
              "endTime": "114.300s",
              "startTime": "112.800s",
              "word": "anlat\u0131r"
            },
            {
              "endTime": "114.300s",
              "startTime": "114.300s",
              "word": "m\u0131s\u0131n"
            }
          ]
        }
      ]
    },
    {
      "alternatives": [
        {
          "confidence": 0.7935361,
          "transcript": " sevdi\u011fim yolday\u0131m ben de senin sevgilin vard\u0131 sevgilim benim Sen benim sevgilim benden ayr\u0131ld\u0131 gitti bak\u0131\u015f beni ba\u015fka kar\u015f\u0131ma \u00e7\u0131kt\u0131",
          "words": [
            {
              "endTime": "121.200s",
              "startTime": "120.500s",
              "word": "sevdi\u011fim"
            },
            {
              "endTime": "121.600s",
              "startTime": "121.200s",
              "word": "yolday\u0131m"
            },
            {
              "endTime": "121.900s",
              "startTime": "121.600s",
              "word": "ben"
            },
            {
              "endTime": "122s",
              "startTime": "121.900s",
              "word": "de"
            },
            {
              "endTime": "122.600s",
              "startTime": "122s",
              "word": "senin"
            },
            {
              "endTime": "123.200s",
              "startTime": "122.600s",
              "word": "sevgilin"
            },
            {
              "endTime": "123.700s",
              "startTime": "123.200s",
              "word": "vard\u0131"
            },
            {
              "endTime": "124.800s",
              "startTime": "123.700s",
              "word": "sevgilim"
            },
            {
              "endTime": "125.200s",
              "startTime": "124.800s",
              "word": "benim"
            },
            {
              "endTime": "125.500s",
              "startTime": "125.200s",
              "word": "Sen"
            },
            {
              "endTime": "125.800s",
              "startTime": "125.500s",
              "word": "benim"
            },
            {
              "endTime": "126.200s",
              "startTime": "125.800s",
              "word": "sevgilim"
            },
            {
              "endTime": "126.400s",
              "startTime": "126.200s",
              "word": "benden"
            },
            {
              "endTime": "126.700s",
              "startTime": "126.400s",
              "word": "ayr\u0131ld\u0131"
            },
            {
              "endTime": "126.900s",
              "startTime": "126.700s",
              "word": "gitti"
            },
            {
              "endTime": "127.400s",
              "startTime": "126.900s",
              "word": "bak\u0131\u015f"
            },
            {
              "endTime": "127.700s",
              "startTime": "127.400s",
              "word": "beni"
            },
            {
              "endTime": "128s",
              "startTime": "127.700s",
              "word": "ba\u015fka"
            },
            {
              "endTime": "128.500s",
              "startTime": "128s",
              "word": "kar\u015f\u0131ma"
            },
            {
              "endTime": "128.800s",
              "startTime": "128.500s",
              "word": "\u00e7\u0131kt\u0131"
            }
          ]
        }
      ]
    },
    {
      "alternatives": [
        {
          "confidence": 0.815819,
          "transcript": " o beni b\u0131rakt\u0131 gitti ya kar\u015f\u0131ma \u00e7\u0131kt\u0131",
          "words": [
            {
              "endTime": "130.400s",
              "startTime": "130.400s",
              "word": "o"
            },
            {
              "endTime": "131s",
              "startTime": "130.400s",
              "word": "beni"
            },
            {
              "endTime": "131.300s",
              "startTime": "131s",
              "word": "b\u0131rakt\u0131"
            },
            {
              "endTime": "131.700s",
              "startTime": "131.300s",
              "word": "gitti"
            },
            {
              "endTime": "131.700s",
              "startTime": "131.700s",
              "word": "ya"
            },
            {
              "endTime": "132.100s",
              "startTime": "131.700s",
              "word": "kar\u015f\u0131ma"
            },
            {
              "endTime": "132.500s",
              "startTime": "132.100s",
              "word": "\u00e7\u0131kt\u0131"
            }
          ]
        }
      ]
    }
  ]
}
